nounseed
