Metadata-Version: 2.1
Name: nounseed
Version: 1.0.5
Summary: A package for generating and storing project ideas
Author: psibir
License-File: LICENSE
